{
    "mobileBottomRow": 25,
    "widgetName": "Text_list_comp_desc",
    "displayName": "Text",
    "iconSVG": "/static/media/icon.a47d6d5dbbb718c4dc4b2eb4f218c1b7.svg",
    "searchTags": [
        "typography",
        "paragraph",
        "label"
    ],
    "topRow": 5,
    "bottomRow": 18,
    "parentRowSpace": 10,
    "type": "TEXT_WIDGET",
    "hideCard": false,
    "mobileRightColumn": 14,
    "animateLoading": true,
    "overflow": "TRUNCATE",
    "fontFamily": "{{appsmith.theme.fontFamily.appFont}}",
    "parentColumnSpace": 16.875,
    "dynamicTriggerPathList": [],
    "leftColumn": 0,
    "dynamicBindingPathList": [
        {"key": "truncateButtonColor"},
        {"key": "fontFamily"},
        {"key": "borderRadius"},
        {"key": "text"}
    ],
    "shouldTruncate": false,
    "truncateButtonColor": "{{appsmith.theme.colors.primaryColor}}",
    "text": "{{currentItem.description}}",
    "key": "bvjcyc3h69",
    "isDeprecated": false,
    "rightColumn": 31,
    "textAlign": "LEFT",
    "dynamicHeight": "FIXED",
    "widgetId": "xyew3ja3sg",
    "minWidth": 450,
    "isVisible": true,
    "fontStyle": "",
    "textColor": "#231F20",
    "version": 1,
    "parentId": "tq8kkb316k",
    "tags": [
        "Suggested",
        "Content"
    ],
    "renderMode": "CANVAS",
    "isLoading": false,
    "mobileTopRow": 21,
    "responsiveBehavior": "fill",
    "borderRadius": "{{appsmith.theme.borderRadius.appBorderRadius}}",
    "mobileLeftColumn": 0,
    "maxDynamicHeight": 9000,
    "fontSize": "1rem",
    "minDynamicHeight": 4
}